{
  "files": [
    {
      "sha1": "46276b45e751e07a3dd0c6fd61c0d145429b72cf", 
      "name": "CAT31290713_metasource.xml", 
      "format": "MARC Source", 
      "source": "original", 
      "mtime": "1432906651", 
      "crc32": "e46a0885", 
      "md5": "68309d3900dbb1ec7aefb5e39cab0086", 
      "size": "307"
    }, 
    {
      "sha1": "0da7eb2bff1da78e601ce469d25e8799e73b762c", 
      "name": "CAT31290713_dc.xml", 
      "format": "Dublin Core", 
      "source": "original", 
      "mtime": "1432906651", 
      "crc32": "e0c89531", 
      "md5": "8b0347163bfdef16fb34dd9f5ec02fc4", 
      "size": "1346"
    }, 
    {
      "sha1": "2bc2a3167c6aeea0b2e60066424987ab679133b2", 
      "name": "CAT31290713_marc.xml", 
      "format": "MARC", 
      "source": "original", 
      "mtime": "1432906651", 
      "crc32": "003f4cc3", 
      "md5": "b4bcf913053465d0095106afb4b27336", 
      "size": "4037"
    }, 
    {
      "sha1": "111254890d031e22d0448252b91656f0c1f45309", 
      "name": "CAT31290713_meta.mrc", 
      "format": "MARC Binary", 
      "source": "original", 
      "mtime": "1432906651", 
      "crc32": "cc5d0526", 
      "md5": "86a22e47878aadffc45c886ee7bdc2f0", 
      "size": "1175"
    }, 
    {
      "sha1": "d72f757ab6fc300fbeb52a290c337048c9b4e1cc", 
      "name": "CAT31290713_scandata.xml", 
      "format": "Scandata", 
      "source": "original", 
      "mtime": "1433354767", 
      "crc32": "a7f5b455", 
      "md5": "913ef025e489dbcf1cd5e1ff03926ee9", 
      "size": "63172"
    }, 
    {
      "sha1": "35bb90698872bfdc9da43ac2a8e69197e7d48c24", 
      "name": "CAT31290713_orig_jp2.tar", 
      "format": "Single Page Original JP2 Tar", 
      "source": "original", 
      "mtime": "1433354768", 
      "crc32": "1cf21e0f", 
      "md5": "44688c6b8f1d25df7549def42f6df566", 
      "size": "57446400"
    }, 
    {
      "sha1": "2487ba43ce7c1a4dcb0c95f2e73492186899a0ef", 
      "name": "CAT31290713.gif", 
      "format": "Animated GIF", 
      "source": "derivative", 
      "mtime": "1433356070", 
      "crc32": "ecf0661b", 
      "md5": "23a302b03e01fd4c03c3865b7045d152", 
      "original": "CAT31290713_jp2.zip", 
      "size": "272859"
    }, 
    {
      "sha1": "26325bec338512b14197ab45cb2ccd0803c9414e", 
      "name": "CAT31290713_djvu.txt", 
      "format": "DjVuTXT", 
      "source": "derivative", 
      "mtime": "1433364373", 
      "crc32": "43f67170", 
      "md5": "7d99b9d60113613d88f9b9e1528b98d8", 
      "original": "CAT31290713.djvu", 
      "size": "117672"
    }, 
    {
      "sha1": "ee908e6ec77a8198b409b6ad7fa69be1e42df599", 
      "name": "CAT31290713_bw.pdf", 
      "format": "Grayscale LuraTech PDF", 
      "source": "derivative", 
      "mtime": "1433364363", 
      "crc32": "2c7bc54e", 
      "md5": "74bb1c55465b87e1b259ac6d5557e6ed", 
      "original": "CAT31290713_djvu.xml", 
      "size": "5392498"
    }, 
    {
      "sha1": "614d4f2336333ca54b372bd03d55923c04ac17fb", 
      "name": "CAT31290713_djvu.xml", 
      "format": "Djvu XML", 
      "source": "derivative", 
      "mtime": "1433363316", 
      "crc32": "daa3f9b7", 
      "md5": "6a1d3c30e582b4deb281aa3dc28dfe01", 
      "original": "CAT31290713_abbyy.gz", 
      "size": "1078656"
    }, 
    {
      "sha1": "758d71f8ddad9ff31307827bed1f23680af61512", 
      "name": "CAT31290713_abbyy.gz", 
      "format": "Abbyy GZ", 
      "source": "derivative", 
      "mtime": "1433363285", 
      "crc32": "a363b351", 
      "md5": "c05903fedd64436e364190dde98ab81d", 
      "original": "CAT31290713_jp2.zip", 
      "size": "1659514"
    }, 
    {
      "sha1": "26b829b87d3d3423b512f8458dac0c7dc2103b84", 
      "name": "CAT31290713_jp2.zip", 
      "format": "Single Page Processed JP2 ZIP", 
      "source": "derivative", 
      "mtime": "1433356031", 
      "crc32": "828dc29e", 
      "md5": "6d09301d9bbffb38689a5a011024410e", 
      "original": "CAT31290713_orig_jp2.tar", 
      "size": "45025258"
    }, 
    {
      "sha1": "78e3c78b79225540b3e33ccaea1649b66df964ec", 
      "name": "CAT31290713.epub", 
      "format": "EPUB", 
      "source": "derivative", 
      "mtime": "1433363321", 
      "crc32": "3062c584", 
      "md5": "2d988d42ef29eadb6633be73e9a6d33e", 
      "original": "CAT31290713_abbyy.gz", 
      "size": "49657"
    }, 
    {
      "sha1": "1c17934ce980610e6377434906da7a7a1e64cca2", 
      "name": "CAT31290713.pdf", 
      "format": "Text PDF", 
      "source": "derivative", 
      "mtime": "1433363877", 
      "crc32": "91e0e229", 
      "md5": "4b4b1b81dbbe6b2caadb8294977abbf8", 
      "original": "CAT31290713_djvu.xml", 
      "size": "5741460"
    }, 
    {
      "sha1": "e674cebcd2b16dfc92f46cbe7a503678e2080818", 
      "name": "CAT31290713.djvu", 
      "format": "DjVu", 
      "source": "derivative", 
      "mtime": "1433363539", 
      "crc32": "05c8600d", 
      "md5": "547f30ca0156bad977801eda1da417f8", 
      "original": "CAT31290713_djvu.xml", 
      "size": "3463973"
    }, 
    {
      "sha1": "5908650da4e2885d802732eaedcf3a9560793cd5", 
      "name": "CAT31290713_bhlmets.xml", 
      "format": "Biodiversity Heritage Library METS", 
      "source": "original", 
      "mtime": "1433749236", 
      "crc32": "c6c48f51", 
      "md5": "b6586442de84cfe8529d4b66e511b55f", 
      "size": "23297"
    }, 
    {
      "sha1": "0dc319baeb6e7846a3bc00ec44b0d586ac25340c", 
      "name": "CAT31290713_meta.sqlite", 
      "format": "Metadata", 
      "source": "original", 
      "mtime": "1434008199", 
      "crc32": "86d85b09", 
      "md5": "76c73c15d85c2c32461d9243212a13a1", 
      "size": "6144"
    }, 
    {
      "sha1": "b88917f32c859104b04f00abb9f42bf5da6eae60", 
      "name": "CAT31290713_names.xml", 
      "format": "Name Metadata", 
      "source": "original", 
      "mtime": "1434008196", 
      "crc32": "233aacc1", 
      "md5": "a1421d3993cde1232645d9b876d56973", 
      "size": "14710"
    }, 
    {
      "sha1": "e3d9941ec3ea1f03714a5aae75681c226502d221", 
      "name": "CAT31290713_meta.xml", 
      "format": "Metadata", 
      "source": "original", 
      "mtime": "1435773971", 
      "crc32": "59ecf963", 
      "md5": "027861b92679c245ec40f616e067423d", 
      "size": "2834"
    }, 
    {
      "sha1": "37e3afc722e33445757746b33a4d2081cbcc52d6", 
      "name": "CAT31290713_archive.torrent", 
      "btih": "8442adbae60925c1b6486d39cf7570ee830c2f7e", 
      "format": "Archive BitTorrent", 
      "source": "metadata", 
      "mtime": "1435773972", 
      "crc32": "8ee00ebc", 
      "md5": "6896b610b4e9bdfc07e3683a39118076", 
      "size": "6657"
    }, 
    {
      "source": "original", 
      "md5": "d90f70cfb53e758d61a8e3319cd84af8", 
      "name": "CAT31290713_files.xml", 
      "format": "Metadata"
    }
  ], 
  "uniq": 1757464762, 
  "created": 1446754236, 
  "workable_servers": [
    "ia601307.us.archive.org"
  ], 
  "server": "ia601307.us.archive.org", 
  "item_size": 120371626, 
  "dir": "/6/items/CAT31290713", 
  "metadata": {
    "partner_shiptracking": "NC15_1910_Ga-Gl", 
    "shiptracking": "ST003762", 
    "scanner": "scribe4.beltsville.archive.org", 
    "creator": [
      "W. & T. Smith Company", 
      "Henry G. Gilbert Nursery and Seed Trade Catalog Collection"
    ], 
    "series": "Henry G. Gilbert Nursery and Seed Trade Catalog Collection", 
    "ppi": "500", 
    "subcollection": "henryggilbertnurseryandseedtradecollection", 
    "nal_call_number": "62.61 1910", 
    "operator": "associate-saw-thein@archive.org", 
    "sponsor": "U.S. Department of Agriculture, National Agricultural Library", 
    "copyright_message": "The contributing institution believes that this item is not in copyright.", 
    "contributor": "U.S. Department of Agriculture, National Agricultural Library", 
    "foldoutcount": "0", 
    "scanfee": "100", 
    "subject": [
      "Vegetable gardening Equipment and supplies Catalogs", 
      "Gardening Equipment and supplies Catalogs", 
      "Seeds Catalogs"
    ], 
    "title": "General catalogue of hardy fruits and ornamental trees, shrubs, vines and roses : the product of sixty years' experience", 
    "repub_state": "4", 
    "camera": "Canon EOS 5D Mark II", 
    "invoice": "3", 
    "ocr": "ABBYY FineReader 9.0", 
    "identifier-access": "http://archive.org/details/CAT31290713", 
    "scanningcenter": "beltsville", 
    "description": "Cover title", 
    "identifier-ark": "ark:/13960/t5r81tn9x", 
    "mediatype": "texts", 
    "collection": [
      "usda-nurseryandseedcatalog", 
      "usdanationalagriculturallibrary", 
      "biodiversity", 
      "fedlink", 
      "americana"
    ], 
    "volume": "1910", 
    "repub_seconds": "92", 
    "updater": "associate-manuel-dennis@archive.org", 
    "updatedate": "2015-05-29 13:37:31", 
    "uploader": "associate-manuel-dennis@archive.org", 
    "date": "1910", 
    "republisher": "associate-john-leonard@archive.org", 
    "addeddate": "2015-05-29 13:37:33.921478", 
    "publisher": "Geneva, N.Y. : W. & T. Smith Co.", 
    "publicdate": "2015-05-29 12:36:43", 
    "language": "eng", 
    "page-progression": "lr", 
    "curation": "[curator]admin-shelia-deroche@archive.org[/curator][date]20150701135348[/date][state]approved[/state][comment]invoice201506[/comment]", 
    "notes": "No copyright page found. No table-of-contents pages found.", 
    "imagecount": "40", 
    "identifier": "CAT31290713", 
    "sponsordate": "20150630", 
    "unique_id": "CAT31290713", 
    "scandate": "20150602124956"
  }, 
  "files_count": 21, 
  "d1": "ia601307.us.archive.org"
}