{
  "files": [
    {
      "sha1": "dd8a59794446f8e429e6e5b8b294b62c50ba9049", 
      "name": "CAT31293757_metasource.xml", 
      "format": "MARC Source", 
      "source": "original", 
      "mtime": "1439382422", 
      "crc32": "a3c0faf2", 
      "md5": "70be4ab661b0edbf33bcc62edfd86799", 
      "size": "307"
    }, 
    {
      "sha1": "c1f4101d813d4e999d89f79406d37cb582fed5de", 
      "name": "CAT31293757_dc.xml", 
      "format": "Dublin Core", 
      "source": "original", 
      "mtime": "1439382422", 
      "crc32": "1832b9f6", 
      "md5": "a626fee5cb2732486260d7bde36c00b6", 
      "size": "1611"
    }, 
    {
      "sha1": "8030839dc90d1fcf7226f4628c54294ea7b7d602", 
      "name": "CAT31293757_marc.xml", 
      "format": "MARC", 
      "source": "original", 
      "mtime": "1439382422", 
      "crc32": "b50c081a", 
      "md5": "fcc402268ff77fbd7e4d203b390ac636", 
      "size": "3960"
    }, 
    {
      "sha1": "6d758f77c463532a6f7dae6a9b59762164910d9d", 
      "name": "CAT31293757_meta.mrc", 
      "format": "MARC Binary", 
      "source": "original", 
      "mtime": "1439382422", 
      "crc32": "06fae860", 
      "md5": "389e346049ab6dcbee17fe296536ff01", 
      "size": "1139"
    }, 
    {
      "sha1": "f0385956a0cc608029e2db45043199c333fd449e", 
      "name": "CAT31293757_scandata.xml", 
      "format": "Scandata", 
      "source": "original", 
      "mtime": "1443096393", 
      "crc32": "a918ae4d", 
      "md5": "223f542d14b78be97333d96beccd996f", 
      "size": "107808"
    }, 
    {
      "sha1": "99245e70eae904f57e298a01d1da1e59c8bd76ed", 
      "name": "CAT31293757_orig_jp2.tar", 
      "format": "Single Page Original JP2 Tar", 
      "source": "original", 
      "mtime": "1443096398", 
      "crc32": "0daeede4", 
      "md5": "10c53f0c5e0cf230247d83ccca49318a", 
      "size": "95324160"
    }, 
    {
      "sha1": "920d5861dad08ec14c325db87c2817e0fa87762d", 
      "name": "CAT31293757.djvu", 
      "format": "DjVu", 
      "source": "derivative", 
      "mtime": "1443099573", 
      "crc32": "df58c3c7", 
      "md5": "16585b89d313f3ee9085a7d20f412b86", 
      "original": "CAT31293757_djvu.xml", 
      "size": "6715026"
    }, 
    {
      "sha1": "ade875778b4aef1280491da97db7220f7af2f88e", 
      "name": "CAT31293757.epub", 
      "format": "EPUB", 
      "source": "derivative", 
      "mtime": "1443099070", 
      "crc32": "48942ab9", 
      "md5": "a7bab4b887982f080211e8e44d5fdfbf", 
      "original": "CAT31293757_abbyy.gz", 
      "size": "221290"
    }, 
    {
      "sha1": "680f0274095e987d1d29376fda32ef0ad82f9b71", 
      "name": "CAT31293757_jp2.zip", 
      "format": "Single Page Processed JP2 ZIP", 
      "source": "derivative", 
      "mtime": "1443098130", 
      "crc32": "6fc58afd", 
      "md5": "c265453b94ba246376eb5830b7600ca5", 
      "original": "CAT31293757_orig_jp2.tar", 
      "size": "76369570"
    }, 
    {
      "sha1": "055481c012129e3b3ac60fb037bd7ac1f55bac8c", 
      "name": "CAT31293757_djvu.txt", 
      "format": "DjVuTXT", 
      "source": "derivative", 
      "mtime": "1443100892", 
      "crc32": "27a51ce7", 
      "md5": "c1500fad22087ff20e79e2d199243861", 
      "original": "CAT31293757.djvu", 
      "size": "185671"
    }, 
    {
      "sha1": "82c69031bc7a7de9ef722392b5fd084d58c52667", 
      "name": "CAT31293757.gif", 
      "format": "Animated GIF", 
      "source": "derivative", 
      "mtime": "1443098176", 
      "crc32": "2204502b", 
      "md5": "b9b5f28f546497ecdaa1ddd2796af758", 
      "original": "CAT31293757_jp2.zip", 
      "size": "282356"
    }, 
    {
      "sha1": "fea4a6fcbfc623bf014e09beec71c152659e0a0a", 
      "name": "CAT31293757_bw.pdf", 
      "format": "Grayscale LuraTech PDF", 
      "source": "derivative", 
      "mtime": "1443100878", 
      "crc32": "d174f3d4", 
      "md5": "d65c2b0e3012e0cf1de5a580a0df705b", 
      "original": "CAT31293757_djvu.xml", 
      "size": "11399306"
    }, 
    {
      "sha1": "19d3db22fac7c66f9e3cbe8d54f20c140d53e9c5", 
      "name": "CAT31293757.pdf", 
      "format": "Text PDF", 
      "source": "derivative", 
      "mtime": "1443100089", 
      "crc32": "d5a8212e", 
      "md5": "b20ca71839a3c0fba8f7fa5fdace50bf", 
      "original": "CAT31293757_djvu.xml", 
      "size": "10495973"
    }, 
    {
      "sha1": "7f0091c8ccd7bf9fc007dc986c24de27b8f8c5a1", 
      "name": "CAT31293757_abbyy.gz", 
      "format": "Abbyy GZ", 
      "source": "derivative", 
      "mtime": "1443098921", 
      "crc32": "e7eb56db", 
      "md5": "d2caf2d040fb562700085d8b1632b4ce", 
      "original": "CAT31293757_jp2.zip", 
      "size": "2686792"
    }, 
    {
      "sha1": "98e23df15d2470613b6e7041a9deb2d6943ed126", 
      "name": "CAT31293757_djvu.xml", 
      "format": "Djvu XML", 
      "source": "derivative", 
      "mtime": "1443098997", 
      "crc32": "d3af36ce", 
      "md5": "d9baed99ea18a48604bc322e128e66aa", 
      "original": "CAT31293757_abbyy.gz", 
      "size": "1818483"
    }, 
    {
      "sha1": "559f923a0b00aa1fcf787f74ee69b403c458f421", 
      "name": "CAT31293757_bhlmets.xml", 
      "format": "Biodiversity Heritage Library METS", 
      "source": "original", 
      "mtime": "1443425179", 
      "crc32": "a9ee6278", 
      "md5": "5b7b7cfd9c297321029ad09cbae1f8bc", 
      "size": "39605"
    }, 
    {
      "sha1": "09eafbcab7fa2bb1b90d1acd444c27190edba715", 
      "name": "CAT31293757_meta.sqlite", 
      "format": "Metadata", 
      "source": "original", 
      "mtime": "1443514218", 
      "crc32": "9ca1b475", 
      "md5": "89be361fb256bd546218e1895561db95", 
      "size": "6144"
    }, 
    {
      "sha1": "097c89b8f794fb837bd8f5444e6f148ee2dcb400", 
      "name": "CAT31293757_names.xml", 
      "format": "Name Metadata", 
      "source": "original", 
      "mtime": "1443512746", 
      "crc32": "c932ec05", 
      "md5": "7c1945a639453feffabfbcf2e3ff98d8", 
      "size": "55317"
    }, 
    {
      "sha1": "1fad529f5bdf8e29e64bbd05b77e09caa05985c9", 
      "name": "CAT31293757_meta.xml", 
      "format": "Metadata", 
      "source": "original", 
      "mtime": "1446573034", 
      "crc32": "ef1af272", 
      "md5": "a461fcf20dc782979c038a5e16069c93", 
      "size": "2957"
    }, 
    {
      "sha1": "5950736f7b4fb6ad50034476b2a53ac73d7f4181", 
      "name": "CAT31293757_archive.torrent", 
      "btih": "1982bfc77f1dc06d49cb6ab4895e3b25ed1fe840", 
      "format": "Archive BitTorrent", 
      "source": "metadata", 
      "mtime": "1446573036", 
      "crc32": "9881bdaa", 
      "md5": "1ad6490990b8c07a4bd896a89c021712", 
      "size": "8459"
    }, 
    {
      "source": "original", 
      "md5": "a2c7a6b0dba3ecc4839b5d0e3ba9edc8", 
      "name": "CAT31293757_files.xml", 
      "format": "Metadata"
    }
  ], 
  "uniq": 869822178, 
  "created": 1446751030, 
  "workable_servers": [
    "ia601501.us.archive.org"
  ], 
  "server": "ia601501.us.archive.org", 
  "item_size": 205725934, 
  "dir": "/0/items/CAT31293757", 
  "metadata": {
    "partner_shiptracking": "NC15_1913_Ga-Gl", 
    "shiptracking": "ST004164", 
    "scanner": "scribe1.beltsville.archive.org", 
    "creator": [
      "Glen St. Mary Nurseries", 
      "Taber, G. L", 
      "Henry G. Gilbert Nursery and Seed Trade Catalog Collection"
    ], 
    "series": "Henry G. Gilbert Nursery and Seed Trade Catalog Collection", 
    "ppi": "500", 
    "subcollection": "henryggilbertnurseryandseedtradecollection", 
    "nal_call_number": "62.17 1913", 
    "operator": "associate-mark-kanaskie@archive.org", 
    "sponsor": "U.S. Department of Agriculture, National Agricultural Library", 
    "copyright_message": "The contributing institution believes that this item is not in copyright.", 
    "contributor": "U.S. Department of Agriculture, National Agricultural Library", 
    "foldoutcount": "2", 
    "scanfee": "100", 
    "subject": [
      "Nursery stock Florida Catalogs", 
      "Fruit trees Seedlings Catalogs", 
      "Fruit Catalogs", 
      "Plants, Ornamental Catalogs", 
      "Shrubs Catalogs", 
      "Trees Seedlings Catalogs"
    ], 
    "title": "Glen Saint Mary Nurseries Company [catalog] : 1913", 
    "repub_state": "4", 
    "foldout_seconds": "214", 
    "camera": "Canon EOS 5D Mark II", 
    "invoice": "3", 
    "ocr": "ABBYY FineReader 11.0", 
    "identifier-access": "http://archive.org/details/CAT31293757", 
    "scanningcenter": "beltsville", 
    "description": "Includes index", 
    "identifier-ark": "ark:/13960/t0100tg3r", 
    "mediatype": "texts", 
    "collection": [
      "usda-nurseryandseedcatalog", 
      "usdanationalagriculturallibrary", 
      "biodiversity", 
      "fedlink", 
      "americana"
    ], 
    "volume": "1913", 
    "updater": "associate-manuel-dennis@archive.org", 
    "updatedate": "2015-08-12 12:27:02", 
    "uploader": "associate-manuel-dennis@archive.org", 
    "date": "1913", 
    "republisher": "associate-phillip-gordon@archive.org", 
    "addeddate": "2015-08-12 12:27:04.122229", 
    "foldout-operator": "associate-marc-adona@archive.org", 
    "publisher": "Glen Saint Mary, Fla. : Glen Saint Mary Nurseries", 
    "publicdate": "2015-08-12 11:30:07", 
    "language": "eng", 
    "page-progression": "lr", 
    "curation": "[curator]admin-shelia-deroche@archive.org[/curator][date]20151103175029[/date][state]approved[/state][comment]invoice201510[/comment]", 
    "notes": "No copyright page found. No table-of-contents pages found.", 
    "imagecount": "70", 
    "identifier": "CAT31293757", 
    "unique_id": "CAT31293757", 
    "scandate": "20150812142734"
  }, 
  "files_count": 21, 
  "d1": "ia601501.us.archive.org"
}