{
  "files": [
    {
      "sha1": "5e1f54fc6e6f900a19c6b87ff4a5ca37feb61721", 
      "name": "CAT31289963_metasource.xml", 
      "format": "MARC Source", 
      "source": "original", 
      "mtime": "1430242183", 
      "crc32": "f60d3b12", 
      "md5": "47e5d732b2f4da63cb9260b1b1bb2954", 
      "size": "307"
    }, 
    {
      "sha1": "d0ba176567c6a93a705dc2e41a642f47a1e80a60", 
      "name": "CAT31289963_meta.mrc", 
      "format": "MARC Binary", 
      "source": "original", 
      "mtime": "1430242183", 
      "crc32": "d4f76a07", 
      "md5": "12c2394dcdced50b67ee77059a57e51a", 
      "size": "1294"
    }, 
    {
      "sha1": "e7308b19ee14d353b12846e0e4a218cccf0fca82", 
      "name": "CAT31289963_dc.xml", 
      "format": "Dublin Core", 
      "source": "original", 
      "mtime": "1430242183", 
      "crc32": "75c496d4", 
      "md5": "5e48a368fe5dea312e6ccb96f2bcfd82", 
      "size": "1635"
    }, 
    {
      "sha1": "bf574d41710bf5be67f826de61afb1ef7dd4a473", 
      "name": "CAT31289963_marc.xml", 
      "format": "MARC", 
      "source": "original", 
      "mtime": "1430242183", 
      "crc32": "b3629244", 
      "md5": "893cc36f704b6caa4848bd3f0dda4060", 
      "size": "4336"
    }, 
    {
      "sha1": "5869113c26d3be268738bb43d0c1845f20f3fb65", 
      "name": "CAT31289963_orig_jp2.tar", 
      "format": "Single Page Original JP2 Tar", 
      "source": "original", 
      "mtime": "1430398553", 
      "crc32": "4e059f64", 
      "md5": "fb054c46747a647a8d0c487574fcbcfb", 
      "size": "149534720"
    }, 
    {
      "sha1": "2aae39614736cce5ffeeb834db6193d7d24f5d5b", 
      "name": "CAT31289963_scandata.xml", 
      "format": "Scandata", 
      "source": "original", 
      "mtime": "1430398549", 
      "crc32": "7ed00a35", 
      "md5": "ceef3f69df17c09267c55eff4f41a27e", 
      "size": "208799"
    }, 
    {
      "sha1": "668f3e2fb9a0e7d6d3c68d40ed51afedb41a2146", 
      "name": "CAT31289963_bw.pdf", 
      "format": "Grayscale LuraTech PDF", 
      "source": "derivative", 
      "mtime": "1430411081", 
      "crc32": "707f8058", 
      "md5": "0f0161d1ea9be201715842b01bd66da1", 
      "original": "CAT31289963_djvu.xml", 
      "size": "14893614"
    }, 
    {
      "sha1": "ecb479cc508847233402621c134836b0ad3ffaa3", 
      "name": "CAT31289963_djvu.xml", 
      "format": "Djvu XML", 
      "source": "derivative", 
      "mtime": "1430408791", 
      "crc32": "e47d54ce", 
      "md5": "ea7bd0e14e7af022e629d291e11689aa", 
      "original": "CAT31289963_abbyy.gz", 
      "size": "5828761"
    }, 
    {
      "sha1": "8fe23d179839f6b0e0ff88ec4ebff398843ec317", 
      "name": "CAT31289963_abbyy.gz", 
      "format": "Abbyy GZ", 
      "source": "derivative", 
      "mtime": "1430408647", 
      "crc32": "b89df595", 
      "md5": "2a7039dac78b75961a2e1317f93802e9", 
      "original": "CAT31289963_jp2.zip", 
      "size": "9234627"
    }, 
    {
      "sha1": "4b22109fceb4d85b3100aa030a18af8d09009f36", 
      "name": "CAT31289963.pdf", 
      "format": "Text PDF", 
      "source": "derivative", 
      "mtime": "1430410054", 
      "crc32": "56aa426e", 
      "md5": "576465ebc5753f8b8ad5a7126ca7d3b8", 
      "original": "CAT31289963_djvu.xml", 
      "size": "14540402"
    }, 
    {
      "sha1": "3f2e86459e80d445447eec51cc79ce24cc6fe468", 
      "name": "CAT31289963_jp2.zip", 
      "format": "Single Page Processed JP2 ZIP", 
      "source": "derivative", 
      "mtime": "1430400942", 
      "crc32": "764221ba", 
      "md5": "a929c6df2bab267e0c67682746b64373", 
      "original": "CAT31289963_orig_jp2.tar", 
      "size": "97234194"
    }, 
    {
      "sha1": "0b26e4f0333c1e99135d564b4637a030bf723c5f", 
      "name": "CAT31289963.djvu", 
      "format": "DjVu", 
      "source": "derivative", 
      "mtime": "1430409303", 
      "crc32": "d11c8092", 
      "md5": "4cfeb4e727d33dd9461379e83428bafe", 
      "original": "CAT31289963_djvu.xml", 
      "size": "9441705"
    }, 
    {
      "sha1": "34fb2540b968db70afdd1a12dcf53aefd1b32d4d", 
      "name": "CAT31289963.epub", 
      "format": "EPUB", 
      "source": "derivative", 
      "mtime": "1430408808", 
      "crc32": "f49c11da", 
      "md5": "ad7a54924fbefd134336c52f72938af8", 
      "original": "CAT31289963_abbyy.gz", 
      "size": "257639"
    }, 
    {
      "sha1": "a2d823e0418036ab0f73e7c03d42ba9f71144d51", 
      "name": "CAT31289963.gif", 
      "format": "Animated GIF", 
      "source": "derivative", 
      "mtime": "1430400961", 
      "crc32": "45d5fd1f", 
      "md5": "1f138fabda2700215d0fc14807eab7c8", 
      "original": "CAT31289963_jp2.zip", 
      "size": "305318"
    }, 
    {
      "sha1": "48a08f99135ba025ab5a7efc211dc37e40a84284", 
      "name": "CAT31289963_djvu.txt", 
      "format": "DjVuTXT", 
      "source": "derivative", 
      "mtime": "1430411098", 
      "crc32": "9a1fcbf2", 
      "md5": "7a2d99bb6785fe79fe6f723d38b1f8f7", 
      "original": "CAT31289963.djvu", 
      "size": "650795"
    }, 
    {
      "sha1": "ed2abbfede41402fa1dc1f4f9a84f3f1888680ef", 
      "name": "CAT31289963_bhlmets.xml", 
      "format": "Biodiversity Heritage Library METS", 
      "source": "original", 
      "mtime": "1431328427", 
      "crc32": "d93d5f88", 
      "md5": "d6f17a9756dccc9d1976ec0778274eed", 
      "size": "72837"
    }, 
    {
      "sha1": "8ae93b3cf53d7181235fa51e891c5d36d920bc3a", 
      "name": "CAT31289963_names.xml", 
      "format": "Name Metadata", 
      "source": "original", 
      "mtime": "1431503774", 
      "crc32": "266aa781", 
      "md5": "025d7ce379721c56b2e87efa616dc033", 
      "size": "347749"
    }, 
    {
      "sha1": "7c292d63a2e829247a2852fea5ba2a6505a4b5f2", 
      "name": "CAT31289963_meta.sqlite", 
      "format": "Metadata", 
      "source": "original", 
      "mtime": "1431503777", 
      "crc32": "765a662f", 
      "md5": "adb57dfd650d691fe75abefd8577da39", 
      "size": "6144"
    }, 
    {
      "sha1": "6b6e8c47d8514e55ba69284ce3a9f9984002ec09", 
      "name": "CAT31289963_meta.xml", 
      "format": "Metadata", 
      "source": "original", 
      "mtime": "1435773977", 
      "crc32": "eb71339b", 
      "md5": "d57d78b96e372a1102b3d7a7ced1c080", 
      "size": "2936"
    }, 
    {
      "sha1": "cd66832c66f037a1c3521e20d1ae1dff26dbe52e", 
      "name": "CAT31289963_archive.torrent", 
      "btih": "7dffe415ac8507bc96a6b8b8a56ffb625c26c7bd", 
      "format": "Archive BitTorrent", 
      "source": "metadata", 
      "mtime": "1435773980", 
      "crc32": "4d0e81d0", 
      "md5": "b23b6d63b1f1da4d6a0625a1ea2e128c", 
      "size": "10082"
    }, 
    {
      "source": "original", 
      "md5": "a77a0d66aa91ad0f60527b99c41494b9", 
      "name": "CAT31289963_files.xml", 
      "format": "Metadata"
    }
  ], 
  "uniq": 692639429, 
  "created": 1446753726, 
  "workable_servers": [
    "ia600505.us.archive.org"
  ], 
  "server": "ia600505.us.archive.org", 
  "item_size": 302577894, 
  "dir": "/6/items/CAT31289963", 
  "metadata": {
    "partner_shiptracking": "NC15_1909_F", 
    "shiptracking": "ST003575", 
    "scanner": "scribe1.beltsville.archive.org", 
    "creator": [
      "Fancher Creek Nurseries", 
      "Roeding, George Christian, 1868-1928", 
      "Henry G. Gilbert Nursery and Seed Trade Catalog Collection"
    ], 
    "series": "Henry G. Gilbert Nursery and Seed Trade Catalog Collection", 
    "ppi": "350", 
    "subcollection": "henryggilbertnurseryandseedtradecollection", 
    "nal_call_number": "62.09", 
    "operator": "associate-mark-kanaskie@archive.org", 
    "sponsor": "U.S. Department of Agriculture, National Agricultural Library", 
    "copyright_message": "The contributing institution believes that this item is not in copyright.", 
    "contributor": "U.S. Department of Agriculture, National Agricultural Library", 
    "foldoutcount": "0", 
    "scanfee": "100", 
    "subject": [
      "Nursery stock California Fresno Catalogs", 
      "Fruit trees Seedlings Catalogs", 
      "Fruit Catalogs", 
      "Trees Seedlings Catalogs", 
      "Flowering shrubs Catalogs", 
      "Plants, Ornamental Catalogs"
    ], 
    "title": "California horticulture : the fruit growers' guide", 
    "repub_state": "4", 
    "camera": "Canon EOS 5D Mark II", 
    "invoice": "3", 
    "ocr": "ABBYY FineReader 9.0", 
    "identifier-access": "http://archive.org/details/CAT31289963", 
    "scanningcenter": "beltsville", 
    "description": "Includes index", 
    "identifier-ark": "ark:/13960/t4jm5pg4f", 
    "mediatype": "texts", 
    "collection": [
      "usda-nurseryandseedcatalog", 
      "usdanationalagriculturallibrary", 
      "biodiversity", 
      "fedlink", 
      "americana"
    ], 
    "volume": "1909", 
    "repub_seconds": "643", 
    "updater": "associate-manuel-dennis@archive.org", 
    "updatedate": "2015-04-28 17:29:43", 
    "uploader": "associate-manuel-dennis@archive.org", 
    "date": "1909", 
    "republisher": "associate-marc-adona@archive.org", 
    "addeddate": "2015-04-28 17:29:45.765307", 
    "publisher": "Fresno, Calif. : George C. Roeding", 
    "publicdate": "2015-04-28 16:36:45", 
    "language": "eng", 
    "page-progression": "lr", 
    "curation": "[curator]admin-shelia-deroche@archive.org[/curator][date]20150701134827[/date][state]approved[/state][comment]invoice201506[/comment]", 
    "notes": "No copyright page found. No table-of-contents pages found.", 
    "imagecount": "132", 
    "identifier": "CAT31289963", 
    "sponsordate": "20150630", 
    "unique_id": "CAT31289963", 
    "scandate": "20150429160935"
  }, 
  "files_count": 21, 
  "d1": "ia600505.us.archive.org"
}