{
  "files": [
    {
      "sha1": "57e969e6217bac579d363a1210da154024c010a0", 
      "name": "pricelist1920citr_dc.xml", 
      "format": "Dublin Core", 
      "source": "original", 
      "mtime": "1387291693", 
      "crc32": "360e2ec2", 
      "md5": "d6305afaf675d37dd8ed1baa27b4879a", 
      "size": "1529"
    }, 
    {
      "sha1": "6e3d902041ceed33f2ddc9cd2be3a6fc5307c816", 
      "name": "pricelist1920citr_metasource.xml", 
      "format": "MARC Source", 
      "source": "original", 
      "mtime": "1387291693", 
      "crc32": "9959060c", 
      "md5": "d99303b77fc810438008d1a52b7930fd", 
      "size": "315"
    }, 
    {
      "sha1": "862b04031f64f1fe66bcb2f521c751b818e3e731", 
      "name": "pricelist1920citr_marc.xml", 
      "format": "MARC", 
      "source": "original", 
      "mtime": "1387291693", 
      "crc32": "bd6a1866", 
      "md5": "2e9848e339878d8805a6377ae7228981", 
      "size": "4040"
    }, 
    {
      "sha1": "6c3aba2b792e55c7633f14f90e214ab5feab8efe", 
      "name": "pricelist1920citr_meta.mrc", 
      "format": "MARC Binary", 
      "source": "original", 
      "mtime": "1387291693", 
      "crc32": "7799c6b9", 
      "md5": "d4d18fe6d17d479e7530def0ee27417b", 
      "size": "1152"
    }, 
    {
      "sha1": "bfe1cc4bb42abdfea355335004dce12d7a526a53", 
      "name": "pricelist1920citr_orig_jp2.tar", 
      "format": "Single Page Original JP2 Tar", 
      "source": "original", 
      "mtime": "1387493509", 
      "crc32": "78865af0", 
      "md5": "42c0c0b35789c447d8e27ad9b7b6a47e", 
      "size": "4689920"
    }, 
    {
      "sha1": "38cc115ab20ecc41656550f7ef98d78d306e9ea2", 
      "name": "pricelist1920citr_scandata.xml", 
      "format": "Scandata", 
      "source": "original", 
      "mtime": "1387493509", 
      "crc32": "6c8e2b98", 
      "md5": "f8e8c63a15ebf1291927288471befb6c", 
      "size": "7779"
    }, 
    {
      "sha1": "128f6b6be9ac6ee72dbedd465b1171155af435a1", 
      "name": "pricelist1920citr.djvu", 
      "format": "DjVu", 
      "source": "derivative", 
      "mtime": "1387493723", 
      "crc32": "fd1596e4", 
      "md5": "9e5391f9151ccf2fc521f83308f1628c", 
      "original": "pricelist1920citr_djvu.xml", 
      "size": "57007"
    }, 
    {
      "sha1": "c19591e07387b9a9e6df75dc2a45865fc0009b8d", 
      "name": "pricelist1920citr.epub", 
      "format": "EPUB", 
      "source": "derivative", 
      "mtime": "1387493708", 
      "crc32": "652d9afd", 
      "md5": "9386dcfbf4275fbdb10af3f1f2ee9448", 
      "original": "pricelist1920citr_abbyy.gz", 
      "size": "124722"
    }, 
    {
      "sha1": "9c612390aa305c2be4481ab840cbc29dd431f423", 
      "name": "pricelist1920citr_abbyy.gz", 
      "format": "Abbyy GZ", 
      "source": "derivative", 
      "mtime": "1387493696", 
      "crc32": "c63de8a8", 
      "md5": "be36698f6c91386b83206dc8f2eac71a", 
      "original": "pricelist1920citr_jp2.zip", 
      "size": "28645"
    }, 
    {
      "sha1": "41e5c0662350862a4820950e114dc4d0f09e21bb", 
      "name": "pricelist1920citr.pdf", 
      "format": "Text PDF", 
      "source": "derivative", 
      "mtime": "1387493743", 
      "crc32": "0fda9c27", 
      "md5": "daa966982757f55319bbcb58879a0f2f", 
      "original": "pricelist1920citr_djvu.xml", 
      "size": "125947"
    }, 
    {
      "sha1": "916ee54c5d5a6a7b83ba8514614e4f40f3ac095e", 
      "name": "pricelist1920citr.gif", 
      "format": "Animated GIF", 
      "source": "derivative", 
      "mtime": "1387493644", 
      "crc32": "2022f48c", 
      "md5": "3cb89fe36a369154b37a6c504b33c9b3", 
      "original": "pricelist1920citr_jp2.zip", 
      "size": "41757"
    }, 
    {
      "sha1": "c4fe9b2730415eae7490f9e76715eed8a5a641a8", 
      "name": "pricelist1920citr_djvu.xml", 
      "format": "Djvu XML", 
      "source": "derivative", 
      "mtime": "1387493702", 
      "crc32": "980ada97", 
      "md5": "5dc4b585cb9af040bc5ee2f4246703b3", 
      "original": "pricelist1920citr_abbyy.gz", 
      "size": "27219"
    }, 
    {
      "sha1": "795565bde3bad6cdb505aa355b9ed6645b5795c8", 
      "name": "pricelist1920citr_djvu.txt", 
      "format": "DjVuTXT", 
      "source": "derivative", 
      "mtime": "1387493749", 
      "crc32": "0b1c37e8", 
      "md5": "495ec45761e7c62f18424cad3aaaae3b", 
      "original": "pricelist1920citr.djvu", 
      "size": "2066"
    }, 
    {
      "sha1": "9ec4f812acbcf29aba7ffb2a46eca46dcf54f33b", 
      "name": "pricelist1920citr_jp2.zip", 
      "format": "Single Page Processed JP2 ZIP", 
      "source": "derivative", 
      "mtime": "1387493637", 
      "crc32": "7b23a401", 
      "md5": "a4e6e1890804ac7761e85a1692cb9cd2", 
      "original": "pricelist1920citr_orig_jp2.tar", 
      "size": "3063646"
    }, 
    {
      "sha1": "2be95b9ecc58e7349862015e3250284fed8b8af7", 
      "name": "pricelist1920citr_meta.xml", 
      "format": "Metadata", 
      "source": "original", 
      "mtime": "1418948183", 
      "crc32": "e7fc58f0", 
      "md5": "3e5ffde123a41f12f472391aeef76041", 
      "size": "3128"
    }, 
    {
      "sha1": "9e93a127efdba6cc256bbb59e8ca88e3f4c2fc4b", 
      "name": "pricelist1920citr_archive.torrent", 
      "btih": "953213791308bdebdec2986bbc82bb1aec52397b", 
      "format": "Archive BitTorrent", 
      "source": "metadata", 
      "mtime": "1418948184", 
      "crc32": "d3a30805", 
      "md5": "1e1ad8550bf69a83a21a2c62eb705908", 
      "size": "3786"
    }, 
    {
      "source": "original", 
      "md5": "8939f9c2a5d3681455a4303655afffd1", 
      "name": "pricelist1920citr_files.xml", 
      "format": "Metadata"
    }
  ], 
  "uniq": 379082743, 
  "created": 1446721063, 
  "workable_servers": [
    "ia601005.us.archive.org"
  ], 
  "server": "ia601005.us.archive.org", 
  "item_size": 8182658, 
  "dir": "/27/items/pricelist1920citr", 
  "metadata": {
    "partner_shiptracking": "NC14_0047a", 
    "shiptracking": "ST000731", 
    "scanner": "scribe1.beltsville.archive.org", 
    "creator": [
      "Citronelle Nursery and Orchard Co", 
      "Henry G. Gilbert Nursery and Seed Trade Catalog Collection"
    ], 
    "series": "Henry G. Gilbert Nursery and Seed Trade Catalog Collection", 
    "ppi": "500", 
    "nal_call_number": "62.01 1920", 
    "operator": "associate-mang-pau@archive.org", 
    "curatestate": "freeze", 
    "sponsor": "U.S. Department of Agriculture, National Agricultural Library", 
    "copyright_message": "The contributing institution believes that this item is not in copyright", 
    "contributor": "U.S. Department of Agriculture, National Agricultural Library", 
    "foldoutcount": "0", 
    "scanfee": "100", 
    "subject": [
      "Nurseries (Horticulture) Alabama Citronelle Catalogs", 
      "Fruit Alabama Citronelle Catalogs", 
      "Nut trees Alabama Citronelle Catalogs", 
      "Fruit trees Alabama Citronelle Catalogs", 
      "Nursery stock Alabama Citronelle Catalogs", 
      "Citronelle Nursery and Orchard Co", 
      "Nurseries (Horticulture)", 
      "Fruit", 
      "Nut trees", 
      "Fruit trees", 
      "Nursery stock"
    ], 
    "call_number": "CAT31134203", 
    "title": "Price list", 
    "repub_state": "4", 
    "camera": "Canon EOS 5D Mark II", 
    "invoice": "3", 
    "ocr": "ABBYY FineReader 9.0", 
    "identifier-access": "http://archive.org/details/pricelist1920citr", 
    "scanningcenter": "beltsville", 
    "description": "\"1920 1921.\"", 
    "subcolletion": "henryggilbertnurseryandseedtradecollection", 
    "identifier-ark": "ark:/13960/t3613gb26", 
    "mediatype": "texts", 
    "collection": [
      "usda-nurseryandseedcatalog", 
      "usdanationalagriculturallibrary", 
      "fedlink", 
      "americana", 
      "biodiversity"
    ], 
    "volume": "1920", 
    "repub_seconds": "156", 
    "updater": "associate-adrianna-flores@archive.org", 
    "updatedate": "2013-12-17 14:48:13", 
    "uploader": "associate-adrianna-flores@archive.org", 
    "date": "1920", 
    "republisher": "associate-karina-martinez@archive.org", 
    "addeddate": "2013-12-17 14:48:16.060799", 
    "publisher": "Citronelle, Ala. : Citronelle Nursery and Orchard Co.", 
    "publicdate": "2013-12-17 13:46:44", 
    "language": "eng", 
    "page-progression": "lr", 
    "curation": "[curator]admin-shelia-deroche@archive.org[/curator][date]20140604163426[/date][state]approved[/state][comment]invoice201405[/comment]", 
    "imagecount": "6", 
    "identifier": "pricelist1920citr", 
    "sponsordate": "20140531", 
    "unique_id": "CAT31134203", 
    "scandate": "20131218203303"
  }, 
  "files_count": 17, 
  "d1": "ia601005.us.archive.org"
}