{
  "files": [
    {
      "sha1": "b724f461051ed9d743464bb772990f0361afc45a", 
      "name": "pitchermandasaut1895pitc_metasource.xml", 
      "format": "MARC Source", 
      "source": "original", 
      "mtime": "1407426220", 
      "crc32": "377b285c", 
      "md5": "72bbde9326a332e5a875bf13ba02aa51", 
      "size": "320"
    }, 
    {
      "sha1": "dc493c6deba1991c1a2bec75301b0d6621664d11", 
      "name": "pitchermandasaut1895pitc_marc.xml", 
      "format": "MARC", 
      "source": "original", 
      "mtime": "1407426220", 
      "crc32": "d506f0e1", 
      "md5": "873ed8198d286013b17f930d0336d03f", 
      "size": "3792"
    }, 
    {
      "sha1": "ec9f0aa1d9446f7e30ef4f0632559f486c6a2d57", 
      "name": "pitchermandasaut1895pitc_meta.mrc", 
      "format": "MARC Binary", 
      "source": "original", 
      "mtime": "1407426220", 
      "crc32": "0add817c", 
      "md5": "4a028c195c55c7c0344b8e1d5a2dfab3", 
      "size": "1128"
    }, 
    {
      "sha1": "22487b6dd3f092e6979f31bec46f8acbb6a24d3e", 
      "name": "pitchermandasaut1895pitc_dc.xml", 
      "format": "Dublin Core", 
      "source": "original", 
      "mtime": "1407426220", 
      "crc32": "ade50224", 
      "md5": "202b4b928a902de07f2227dd03bb5802", 
      "size": "1665"
    }, 
    {
      "sha1": "fff0626a9157d9ef9d08008ce78cc07f32445aab", 
      "name": "pitchermandasaut1895pitc_scandata.xml", 
      "format": "Scandata", 
      "source": "original", 
      "mtime": "1407950614", 
      "crc32": "5e53091c", 
      "md5": "c3cba6bff3ca2f1c758af3dd1f52629f", 
      "size": "68182"
    }, 
    {
      "sha1": "d0ae79fb567b71ac674f1f3c00ce8e86b82aff44", 
      "name": "pitchermandasaut1895pitc_orig_jp2.tar", 
      "format": "Single Page Original JP2 Tar", 
      "source": "original", 
      "mtime": "1407950615", 
      "crc32": "7eec8445", 
      "md5": "edff2f3404616f3a1ea31a3afc8cdfa1", 
      "size": "64686080"
    }, 
    {
      "sha1": "9ad6a317cea16d8457a3a24df0a5d26670e54f0d", 
      "name": "pitchermandasaut1895pitc.epub", 
      "format": "EPUB", 
      "source": "derivative", 
      "mtime": "1407952885", 
      "crc32": "a466a408", 
      "md5": "e1051797d2473652caf64d4727c0d675", 
      "original": "pitchermandasaut1895pitc_abbyy.gz", 
      "size": "1128339"
    }, 
    {
      "sha1": "3f91e3c2995704bc51fdf83c7d4806bc3cdb4453", 
      "name": "pitchermandasaut1895pitc.pdf", 
      "format": "Text PDF", 
      "source": "derivative", 
      "mtime": "1407953495", 
      "crc32": "d6a1118d", 
      "md5": "cefd64184e5bab76f8fde56b2f8b284f", 
      "original": "pitchermandasaut1895pitc_djvu.xml", 
      "size": "8648493"
    }, 
    {
      "sha1": "24a1c27bfe0f52e18d42418b2eefee30f2c13f62", 
      "name": "pitchermandasaut1895pitc.gif", 
      "format": "Animated GIF", 
      "source": "derivative", 
      "mtime": "1407951678", 
      "crc32": "d3452af0", 
      "md5": "96c03b92b843cd29ee0b1c2446393f5d", 
      "original": "pitchermandasaut1895pitc_jp2.zip", 
      "size": "316313"
    }, 
    {
      "sha1": "9cd5836ae3e93aa95c99c9005a09d24f912726ea", 
      "name": "pitchermandasaut1895pitc_abbyy.gz", 
      "format": "Abbyy GZ", 
      "source": "derivative", 
      "mtime": "1407952819", 
      "crc32": "fe303309", 
      "md5": "65ef89ffd57085e9ce250eb13890fd72", 
      "original": "pitchermandasaut1895pitc_jp2.zip", 
      "size": "1615965"
    }, 
    {
      "sha1": "ced822607fea79ea0f1122b6bc2a5a5bf691896f", 
      "name": "pitchermandasaut1895pitc_jp2.zip", 
      "format": "Single Page Processed JP2 ZIP", 
      "source": "derivative", 
      "mtime": "1407951652", 
      "crc32": "c7244777", 
      "md5": "d029b1c51ce490995d38181163db3d68", 
      "original": "pitchermandasaut1895pitc_orig_jp2.tar", 
      "size": "56027786"
    }, 
    {
      "sha1": "d1f6e7fe57c56dd6c3b7b9fb8983ebd3251f6c9e", 
      "name": "pitchermandasaut1895pitc_djvu.txt", 
      "format": "DjVuTXT", 
      "source": "derivative", 
      "mtime": "1407953507", 
      "crc32": "95598ea7", 
      "md5": "7f194424459f21ada7989ec920030c6d", 
      "original": "pitchermandasaut1895pitc.djvu", 
      "size": "105963"
    }, 
    {
      "sha1": "e44499f73a86083c3a2aa9f41dd212c95598124a", 
      "name": "pitchermandasaut1895pitc.djvu", 
      "format": "DjVu", 
      "source": "derivative", 
      "mtime": "1407953142", 
      "crc32": "901715e0", 
      "md5": "ec1795a54b7b25b91718b2a2c4c50d2b", 
      "original": "pitchermandasaut1895pitc_djvu.xml", 
      "size": "6054818"
    }, 
    {
      "sha1": "b1f0248c5fd0c1e6f05ad0de1a110eddad930185", 
      "name": "pitchermandasaut1895pitc_djvu.xml", 
      "format": "Djvu XML", 
      "source": "derivative", 
      "mtime": "1407952849", 
      "crc32": "bf25d355", 
      "md5": "da0a5b093a6b7b6d923acf89be7c9e1b", 
      "original": "pitchermandasaut1895pitc_abbyy.gz", 
      "size": "1040339"
    }, 
    {
      "sha1": "ec60bbde92bbe70bb48f2bc87f45e72bb0109f85", 
      "name": "pitchermandasaut1895pitc_meta.xml", 
      "format": "Metadata", 
      "source": "original", 
      "mtime": "1418948098", 
      "crc32": "f2ec84c5", 
      "md5": "1dcd7a06a80a888ae7f29c49178ba9d9", 
      "size": "3008"
    }, 
    {
      "sha1": "0b787358eeae43f9c2b59371a31be79d851e5699", 
      "name": "pitchermandasaut1895pitc_archive.torrent", 
      "btih": "e2de973e2347de0e553d06a419d3c68c2d8de0ff", 
      "format": "Archive BitTorrent", 
      "source": "metadata", 
      "mtime": "1418948100", 
      "crc32": "2aadc282", 
      "md5": "c7e919ffdb9f9c43fb1a3c4984847be4", 
      "size": "6687"
    }, 
    {
      "source": "original", 
      "md5": "2619e908d96e090e5f83e7e57749732b", 
      "name": "pitchermandasaut1895pitc_files.xml", 
      "format": "Metadata"
    }
  ], 
  "uniq": 2079035660, 
  "created": 1446755501, 
  "workable_servers": [
    "ia902303.us.archive.org"
  ], 
  "server": "ia902303.us.archive.org", 
  "item_size": 139708878, 
  "dir": "/30/items/pitchermandasaut1895pitc", 
  "metadata": {
    "partner_shiptracking": "NC14_1895_P", 
    "shiptracking": "ST002160", 
    "scanner": "scribe1.beltsville.archive.org", 
    "creator": [
      "Pitcher & Manda", 
      "Pitcher, James R", 
      "Manda, W. A", 
      "United States Nurseries", 
      "Henry G. Gilbert Nursery and Seed Trade Catalog Collection"
    ], 
    "series": "Henry G. Gilbert Nursery and Seed Trade Catalog Collection.", 
    "ppi": "500", 
    "subcollection": "henryggilbertnurseryandseedtradecollection", 
    "nal_call_number": "62.61", 
    "operator": "associate-marc-adona@archive.org", 
    "sponsor": "U.S. Department of Agriculture, National Agricultural Library", 
    "copyright_message": "The contributing institution believes that this item is not in copyright", 
    "contributor": "U.S. Department of Agriculture, National Agricultural Library", 
    "foldoutcount": "0", 
    "scanfee": "100", 
    "subject": [
      "Nurseries (Horticulture) New Jersey Catalogs", 
      "Flowers Catalogs", 
      "Bulbs (Plants) Catalogs", 
      "Plants, Ornamental Catalogs", 
      "Gardening Equipment and supplies Catalogs"
    ], 
    "call_number": "CAT31281875", 
    "title": "Pitcher & Manda's autumn catalogue of bulbs, plants and seeds", 
    "repub_state": "4", 
    "camera": "Canon EOS 5D Mark II", 
    "invoice": "3", 
    "ocr": "ABBYY FineReader 9.0", 
    "identifier-access": "http://archive.org/details/pitchermandasaut1895pitc", 
    "scanningcenter": "beltsville", 
    "identifier-ark": "ark:/13960/t0qr7kk9j", 
    "mediatype": "texts", 
    "collection": [
      "usda-nurseryandseedcatalog", 
      "usdanationalagriculturallibrary", 
      "fedlink", 
      "americana", 
      "biodiversity"
    ], 
    "volume": "1895", 
    "repub_seconds": "90263", 
    "updater": "associate-manuel-dennis@archive.org", 
    "updatedate": "2014-08-07 15:43:40", 
    "uploader": "associate-manuel-dennis@archive.org", 
    "date": "1895", 
    "republisher": "associate-john-leonard@archive.org", 
    "addeddate": "2014-08-07 15:43:42.515167", 
    "publisher": "Short Hills, New Jersey : Pitcher & Manda", 
    "publicdate": "2014-08-07 14:50:20", 
    "language": "eng", 
    "page-progression": "lr", 
    "curation": "[curator]admin-shelia-deroche@archive.org[/curator][date]20140902193906[/date][state]approved[/state][comment]invoice201408[/comment]", 
    "notes": "No copyright page found. No table-of-contents pages found.", 
    "imagecount": "42", 
    "identifier": "pitchermandasaut1895pitc", 
    "sponsordate": "20140831", 
    "unique_id": "CAT31281875", 
    "scandate": "20140811160849"
  }, 
  "files_count": 17, 
  "d1": "ia902303.us.archive.org"
}