{
  "files": [
    {
      "sha1": "4e83c0435f24541919d728e8d7c3ca96f01b3f80", 
      "name": "CAT31294256_dc.xml", 
      "format": "Dublin Core", 
      "source": "original", 
      "mtime": "1439395774", 
      "crc32": "488fce82", 
      "md5": "82ff363490456086d7c57de6fcd51cde", 
      "size": "1348"
    }, 
    {
      "sha1": "504eddc6384fb3a7e132f69d9b400ba365e9d1f9", 
      "name": "CAT31294256_meta.mrc", 
      "format": "MARC Binary", 
      "source": "original", 
      "mtime": "1439395774", 
      "crc32": "03c3a70a", 
      "md5": "52464f0e87309ff29a3ea9cc19364b39", 
      "size": "991"
    }, 
    {
      "sha1": "c4c67bce71a1b176d12fc8b35fea7f0f663c3d20", 
      "name": "CAT31294256_metasource.xml", 
      "format": "MARC Source", 
      "source": "original", 
      "mtime": "1439395774", 
      "crc32": "a7751980", 
      "md5": "2c6110ff5c63416e7221ab84637f1927", 
      "size": "307"
    }, 
    {
      "sha1": "ff1a9ab21e0f1be8618ab90be2d2a189de8ad346", 
      "name": "CAT31294256_marc.xml", 
      "format": "MARC", 
      "source": "original", 
      "mtime": "1439395774", 
      "crc32": "973b33d2", 
      "md5": "8104490c45751bd4c4a30fae5a29d45b", 
      "size": "3488"
    }, 
    {
      "sha1": "ff8c02a3ad6f98cf12daf965c2aed256249cb34b", 
      "name": "CAT31294256_orig_jp2.tar", 
      "format": "Single Page Original JP2 Tar", 
      "source": "original", 
      "mtime": "1439989617", 
      "crc32": "a98b4b81", 
      "md5": "822398347ed6a7d5c6b79c8ad1e06e69", 
      "size": "3225600"
    }, 
    {
      "sha1": "d12940a5b862d15675a7dee68181c3d38c3548b1", 
      "name": "CAT31294256_scandata.xml", 
      "format": "Scandata", 
      "source": "original", 
      "mtime": "1439989617", 
      "crc32": "a33436b8", 
      "md5": "aad2f35048f0b008823a5c739b6ca6c7", 
      "size": "9686"
    }, 
    {
      "sha1": "8640facaf905170369b03573aa73193281a685e2", 
      "name": "CAT31294256_djvu.txt", 
      "format": "DjVuTXT", 
      "source": "derivative", 
      "mtime": "1439989867", 
      "crc32": "b8de24fd", 
      "md5": "0a35b0d46c2650df88ef01cbd9a8d71f", 
      "original": "CAT31294256.djvu", 
      "size": "950"
    }, 
    {
      "sha1": "0816b8b8eb40db79332fac11ea7a94447b7be475", 
      "name": "CAT31294256.djvu", 
      "format": "DjVu", 
      "source": "derivative", 
      "mtime": "1439989796", 
      "crc32": "243b999d", 
      "md5": "280d0d39f1e25826dce867a8d14d0ef2", 
      "original": "CAT31294256_djvu.xml", 
      "size": "51866"
    }, 
    {
      "sha1": "08533d269476b3a2dbbd38ab317932b8a87f68d5", 
      "name": "CAT31294256_abbyy.gz", 
      "format": "Abbyy GZ", 
      "source": "derivative", 
      "mtime": "1439989770", 
      "crc32": "e4cc3350", 
      "md5": "3c0a764061fbf5b2f397079e994c12f6", 
      "original": "CAT31294256_jp2.zip", 
      "size": "16140"
    }, 
    {
      "sha1": "79a1b7bd8a65f4afec9e1acfc365880380241265", 
      "name": "CAT31294256.pdf", 
      "format": "Text PDF", 
      "source": "derivative", 
      "mtime": "1439989818", 
      "crc32": "50b2b517", 
      "md5": "1e0df0c17aa924b3bfb7dbc319f49d3b", 
      "original": "CAT31294256_djvu.xml", 
      "size": "125839"
    }, 
    {
      "sha1": "cbc35e89889a1f5d19b891cb4ba40236ac85ee41", 
      "name": "CAT31294256_bw.pdf", 
      "format": "Grayscale LuraTech PDF", 
      "source": "derivative", 
      "mtime": "1439989861", 
      "crc32": "153ead54", 
      "md5": "c5b954e2997f1833dc398d7e682efbcb", 
      "original": "CAT31294256_djvu.xml", 
      "size": "90750"
    }, 
    {
      "sha1": "d057223638863c69dda68e9a12fbb8bf6011baa0", 
      "name": "CAT31294256_djvu.xml", 
      "format": "Djvu XML", 
      "source": "derivative", 
      "mtime": "1439989777", 
      "crc32": "179792ba", 
      "md5": "91858021eed1f39ac08991d33b173b04", 
      "original": "CAT31294256_abbyy.gz", 
      "size": "9625"
    }, 
    {
      "sha1": "e63f54662ff8c92cb626b5c884a83fb4eaaa6d49", 
      "name": "CAT31294256.epub", 
      "format": "EPUB", 
      "source": "derivative", 
      "mtime": "1439989778", 
      "crc32": "06acde05", 
      "md5": "d1e43ffc5492e5d2e51123115b76ee51", 
      "original": "CAT31294256_abbyy.gz", 
      "size": "4044"
    }, 
    {
      "sha1": "c4827dda0bb4fddbb3af7f980ad2b79e7d38abcc", 
      "name": "CAT31294256_jp2.zip", 
      "format": "Single Page Processed JP2 ZIP", 
      "source": "derivative", 
      "mtime": "1439989729", 
      "crc32": "e17cf6c8", 
      "md5": "6002b0df437318a5dd18e5af62f04c5a", 
      "original": "CAT31294256_orig_jp2.tar", 
      "size": "2069543"
    }, 
    {
      "sha1": "4d4db897fa594b832445094ee7b7e7d35b3518c4", 
      "name": "CAT31294256.gif", 
      "format": "Animated GIF", 
      "source": "derivative", 
      "mtime": "1439989738", 
      "crc32": "6b531c4f", 
      "md5": "e41b5b27611a1ab27228848b33591fbd", 
      "original": "CAT31294256_jp2.zip", 
      "size": "42042"
    }, 
    {
      "sha1": "be8a3a0549c27a16557231f30b568e9abf0198e3", 
      "name": "CAT31294256_names.xml", 
      "format": "Name Metadata", 
      "source": "original", 
      "mtime": "1440401895", 
      "crc32": "9babbc53", 
      "md5": "14e6ba1eb3923e9c963d75c52140cbf1", 
      "size": "1282"
    }, 
    {
      "sha1": "3b68095f1819f74a510dfa4365c8c9c313f018e7", 
      "name": "CAT31294256_meta.sqlite", 
      "format": "Metadata", 
      "source": "original", 
      "mtime": "1440402919", 
      "crc32": "2d255ba0", 
      "md5": "79bb92428c7f68e9267dd212e01434e4", 
      "size": "6144"
    }, 
    {
      "sha1": "bbb2d13f409183b8394e8da68ffce6d9f317fac9", 
      "name": "CAT31294256_bhlmets.xml", 
      "format": "Biodiversity Heritage Library METS", 
      "source": "original", 
      "mtime": "1440402915", 
      "crc32": "2d28f505", 
      "md5": "a7b955e3eebc6bcd414722d876f1d266", 
      "size": "5293"
    }, 
    {
      "sha1": "f1c1dced7cd324d6f0ce6683f5cad41dcfe92399", 
      "name": "CAT31294256_meta.xml", 
      "format": "Metadata", 
      "source": "original", 
      "mtime": "1444177854", 
      "crc32": "2902d020", 
      "md5": "2c085422b6e37f018b1787b183f35861", 
      "size": "2786"
    }, 
    {
      "sha1": "ea1fa3bddff16a90b47a29be7e248c06e0c0005e", 
      "name": "CAT31294256_archive.torrent", 
      "btih": "e000a26359b9e021dfc6308adced66ec734f24b7", 
      "format": "Archive BitTorrent", 
      "source": "metadata", 
      "mtime": "1444177854", 
      "crc32": "27567c83", 
      "md5": "6b6a857346bca0deae1c66b79ce83935", 
      "size": "4314"
    }, 
    {
      "source": "original", 
      "md5": "dc6859452ea3b7e3e2c1956a6450513f", 
      "name": "CAT31294256_files.xml", 
      "format": "Metadata"
    }
  ], 
  "uniq": 456234441, 
  "created": 1446750903, 
  "workable_servers": [
    "ia601505.us.archive.org"
  ], 
  "server": "ia601505.us.archive.org", 
  "item_size": 5672038, 
  "dir": "/9/items/CAT31294256", 
  "metadata": {
    "partner_shiptracking": "NC15_1913_Sa-Si", 
    "shiptracking": "ST004177", 
    "scanner": "scribe4.beltsville.archive.org", 
    "creator": [
      "Louis F. Scribner (Firm)", 
      "Scribner, Louis F", 
      "Henry G. Gilbert Nursery and Seed Trade Catalog Collection"
    ], 
    "series": "Henry G. Gilbert Nursery and Seed Trade Catalog Collection", 
    "ppi": "500", 
    "subcollection": "henryggilbertnurseryandseedtradecollection", 
    "nal_call_number": "62.09", 
    "operator": "associate-saw-thein@archive.org", 
    "sponsor": "U.S. Department of Agriculture, National Agricultural Library", 
    "copyright_message": "The contributing institution believes that this item is not in copyright.", 
    "contributor": "U.S. Department of Agriculture, National Agricultural Library", 
    "foldoutcount": "0", 
    "scanfee": "100", 
    "subject": [
      "Berries Seedlings Catalogs", 
      "Nursery stock California Pasadena Catalogs", 
      "Nurseries (Horticulture) Prices California Pasadena", 
      "Fruit trees Prices"
    ], 
    "title": "Louis F. Scribner trade list", 
    "repub_state": "4", 
    "camera": "Canon EOS 5D Mark II", 
    "invoice": "3", 
    "ocr": "ABBYY FineReader 9.0", 
    "identifier-access": "http://archive.org/details/CAT31294256", 
    "scanningcenter": "beltsville", 
    "identifier-ark": "ark:/13960/t4qk11s2b", 
    "mediatype": "texts", 
    "collection": [
      "usda-nurseryandseedcatalog", 
      "usdanationalagriculturallibrary", 
      "biodiversity", 
      "fedlink", 
      "americana"
    ], 
    "volume": "1913", 
    "repub_seconds": "72", 
    "updater": "associate-manuel-dennis@archive.org", 
    "updatedate": "2015-08-12 16:09:34", 
    "uploader": "associate-manuel-dennis@archive.org", 
    "date": "1913", 
    "republisher": "associate-john-leonard@archive.org", 
    "addeddate": "2015-08-12 16:09:36.699581", 
    "publisher": "Pasadena, Calif. : Louis F. Scribner", 
    "publicdate": "2015-08-12 15:06:52", 
    "language": "eng", 
    "page-progression": "lr", 
    "curation": "[curator]admin-shelia-deroche@archive.org[/curator][date]20151002134024[/date][state]approved[/state][comment]invoice201509[/comment]", 
    "notes": "No copyright page found. No table-of-contents pages found.", 
    "imagecount": "6", 
    "identifier": "CAT31294256", 
    "sponsordate": "20150930", 
    "unique_id": "CAT31294256", 
    "scandate": "20150817105914"
  }, 
  "files_count": 21, 
  "d1": "ia601505.us.archive.org"
}