{
  "files": [
    {
      "sha1": "1642b7f6528d009e8cfc33acb859752fe1bf1d54", 
      "name": "CAT31294153_meta.mrc", 
      "format": "MARC Binary", 
      "source": "original", 
      "mtime": "1439394979", 
      "crc32": "99b1a751", 
      "md5": "a2c50973a087736ee23b6a0346b4be44", 
      "size": "1207"
    }, 
    {
      "sha1": "993335168d7d4b083a411d72c760e13ca7c04b91", 
      "name": "CAT31294153_metasource.xml", 
      "format": "MARC Source", 
      "source": "original", 
      "mtime": "1439394979", 
      "crc32": "2127a4ae", 
      "md5": "7c2bcfc4af038fbbab552011434f2cb2", 
      "size": "307"
    }, 
    {
      "sha1": "90e622bcc199a5b334cf918af7dca707db60b3e1", 
      "name": "CAT31294153_marc.xml", 
      "format": "MARC", 
      "source": "original", 
      "mtime": "1439394979", 
      "crc32": "ab219a03", 
      "md5": "1f1d5efcdab5a97db80d8947dd1dda5c", 
      "size": "4028"
    }, 
    {
      "sha1": "30e296aada7fb3272708da573a33eeab46adf525", 
      "name": "CAT31294153_dc.xml", 
      "format": "Dublin Core", 
      "source": "original", 
      "mtime": "1439394979", 
      "crc32": "67f6baf7", 
      "md5": "81c2fc4aa24fcc472612da6d093950af", 
      "size": "1529"
    }, 
    {
      "sha1": "cd85c70e84eb15f913c5cfdea14533ff24146e71", 
      "name": "CAT31294153_orig_jp2.tar", 
      "format": "Single Page Original JP2 Tar", 
      "source": "original", 
      "mtime": "1439992873", 
      "crc32": "3488e396", 
      "md5": "38a2424992c180df36968f5c102ca2f9", 
      "size": "20602880"
    }, 
    {
      "sha1": "4231877782fafb473f38ccc3a10ca4fa2234c4db", 
      "name": "CAT31294153_scandata.xml", 
      "format": "Scandata", 
      "source": "original", 
      "mtime": "1439992873", 
      "crc32": "96a36940", 
      "md5": "defe228fc270738d28efb32187dd2926", 
      "size": "32307"
    }, 
    {
      "sha1": "430de1974521b995041ce3ffacce876072094aa1", 
      "name": "CAT31294153.pdf", 
      "format": "Text PDF", 
      "source": "derivative", 
      "mtime": "1439993689", 
      "crc32": "c660ab74", 
      "md5": "140ca67e87689c6f5dbdb52740d516df", 
      "original": "CAT31294153_djvu.xml", 
      "size": "2401286"
    }, 
    {
      "sha1": "385c448b61915aab5957a391a7e65375bd4c53e9", 
      "name": "CAT31294153_abbyy.gz", 
      "format": "Abbyy GZ", 
      "source": "derivative", 
      "mtime": "1439993470", 
      "crc32": "a05c77cb", 
      "md5": "30bef55a94fd1781a92a33e7fb938e28", 
      "original": "CAT31294153_jp2.zip", 
      "size": "885892"
    }, 
    {
      "sha1": "3434a70b8155845fe4d3417edf07fa911a4759f7", 
      "name": "CAT31294153_bw.pdf", 
      "format": "Grayscale LuraTech PDF", 
      "source": "derivative", 
      "mtime": "1439993863", 
      "crc32": "1e6eb984", 
      "md5": "649da657dd9334367d54b616b5253780", 
      "original": "CAT31294153_djvu.xml", 
      "size": "2501341"
    }, 
    {
      "sha1": "005dcf8a36e6a231d9de564380287d577744f595", 
      "name": "CAT31294153_djvu.txt", 
      "format": "DjVuTXT", 
      "source": "derivative", 
      "mtime": "1439993870", 
      "crc32": "6efe0f58", 
      "md5": "45c15ef9118a04e54d4fbe2bf98d0267", 
      "original": "CAT31294153.djvu", 
      "size": "59952"
    }, 
    {
      "sha1": "300e1c699aa99509bc81da58892554744589e793", 
      "name": "CAT31294153_djvu.xml", 
      "format": "Djvu XML", 
      "source": "derivative", 
      "mtime": "1439993491", 
      "crc32": "4f93cf1f", 
      "md5": "37a4bc4872e30a843d23a5a7ad981ece", 
      "original": "CAT31294153_abbyy.gz", 
      "size": "549495"
    }, 
    {
      "sha1": "54c0efabd2b598a4fd619cf21cf151af234565da", 
      "name": "CAT31294153.epub", 
      "format": "EPUB", 
      "source": "derivative", 
      "mtime": "1439993496", 
      "crc32": "ec5de761", 
      "md5": "6401ac664b8ab1055eafcf0e1b9e3626", 
      "original": "CAT31294153_abbyy.gz", 
      "size": "29257"
    }, 
    {
      "sha1": "c10c1cc81433785aea72a61545f49a81a8d1d4fe", 
      "name": "CAT31294153.gif", 
      "format": "Animated GIF", 
      "source": "derivative", 
      "mtime": "1439993224", 
      "crc32": "2c51b8a9", 
      "md5": "af1fd3a043db3f587363c23aeafa440a", 
      "original": "CAT31294153_jp2.zip", 
      "size": "198000"
    }, 
    {
      "sha1": "a119e9399a55d5bdcea18b3e96b3fa83430b5ab0", 
      "name": "CAT31294153_jp2.zip", 
      "format": "Single Page Processed JP2 ZIP", 
      "source": "derivative", 
      "mtime": "1439993209", 
      "crc32": "f9ee6a68", 
      "md5": "89bb45732bceec93659d47ebc9b5f5c0", 
      "original": "CAT31294153_orig_jp2.tar", 
      "size": "14419362"
    }, 
    {
      "sha1": "f036e07b24efdcb9201c146c54daa6c24d4928e9", 
      "name": "CAT31294153.djvu", 
      "format": "DjVu", 
      "source": "derivative", 
      "mtime": "1439993577", 
      "crc32": "235601ff", 
      "md5": "3d31ac5886e0252916c44614ede328f5", 
      "original": "CAT31294153_djvu.xml", 
      "size": "1603693"
    }, 
    {
      "sha1": "958797ccb8c0825d8843de9d1518fe3c666a86d3", 
      "name": "CAT31294153_meta.xml", 
      "format": "Metadata", 
      "source": "original", 
      "mtime": "1440036229", 
      "crc32": "c07a90aa", 
      "md5": "e2c7a8262435f5b47185500fcf3e2e92", 
      "size": "2694"
    }, 
    {
      "sha1": "b097177632a9dc97815bb89cfb36e3196e0d3378", 
      "name": "CAT31294153_bhlmets.xml", 
      "format": "Biodiversity Heritage Library METS", 
      "source": "original", 
      "mtime": "1440401852", 
      "crc32": "1e35c1fb", 
      "md5": "b9f43656799fe0f903330f68b6b3d002", 
      "size": "12801"
    }, 
    {
      "sha1": "afecda9c22e22bb7c1493c30a852c7d3adfd8661", 
      "name": "CAT31294153_meta.sqlite", 
      "format": "Metadata", 
      "source": "original", 
      "mtime": "1440574817", 
      "crc32": "52711530", 
      "md5": "56ac42c82af5fb4e5cf37519e4f677a3", 
      "size": "6144"
    }, 
    {
      "sha1": "5989bde37dd9f4072a6f32f1c08d76ffb7716c26", 
      "name": "CAT31294153_names.xml", 
      "format": "Name Metadata", 
      "source": "original", 
      "mtime": "1440574813", 
      "crc32": "92e71b6c", 
      "md5": "8bf4d3c7a7c78ba6dc05f22e1865cf32", 
      "size": "30218"
    }, 
    {
      "sha1": "46d2a0de8aabaed8becac0b14979a91c24924e9a", 
      "name": "CAT31294153_archive.torrent", 
      "btih": "2743f9311d1347824ef170e0c0594a9f1cf0d225", 
      "format": "Archive BitTorrent", 
      "source": "metadata", 
      "mtime": "1440574820", 
      "crc32": "202f8417", 
      "md5": "f15759a3ce906a0e6185f8feed3bf5cd", 
      "size": "5111"
    }, 
    {
      "source": "original", 
      "md5": "3aeab034cb5d8deb91353ca72ea45213", 
      "name": "CAT31294153_files.xml", 
      "format": "Metadata"
    }
  ], 
  "uniq": 929145560, 
  "created": 1446746124, 
  "workable_servers": [
    "ia601303.us.archive.org"
  ], 
  "server": "ia601303.us.archive.org", 
  "item_size": 43347504, 
  "dir": "/10/items/CAT31294153", 
  "metadata": {
    "partner_shiptracking": "NC15_1913_Pa-Po", 
    "shiptracking": "ST004174", 
    "scanner": "scribe1.beltsville.archive.org", 
    "creator": [
      "F.R. Pierson Company", 
      "Henry G. Gilbert Nursery and Seed Trade Catalog Collection"
    ], 
    "series": "Henry G. Gilbert Nursery and Seed Trade Catalog Collection", 
    "ppi": "350", 
    "subcollection": "henryggilbertnurseryandseedtradecollection", 
    "nal_call_number": "62.61", 
    "operator": "associate-mark-kanaskie@archive.org", 
    "sponsor": "U.S. Department of Agriculture, National Agricultural Library", 
    "copyright_message": "The contributing institution believes that this item is not in copyright.", 
    "contributor": "U.S. Department of Agriculture, National Agricultural Library", 
    "foldoutcount": "0", 
    "scanfee": "100", 
    "subject": [
      "Bulbs (Plants) Prices", 
      "Nursery stock Prices New York (State)", 
      "Nursery stock New York (State) Catalogs", 
      "Plants, Ornamental Catalogs", 
      "Flowers Catalogs", 
      "Bulbs (Plants) Catalogs"
    ], 
    "title": "Wholesale price-list. bulbs and other fall stock", 
    "repub_state": "4", 
    "camera": "Canon EOS 5D Mark II", 
    "invoice": "3", 
    "ocr": "ABBYY FineReader 9.0", 
    "identifier-access": "http://archive.org/details/CAT31294153", 
    "scanningcenter": "beltsville", 
    "description": "Cover title", 
    "identifier-ark": "ark:/13960/t6qz5vg3k", 
    "mediatype": "texts", 
    "collection": [
      "usda-nurseryandseedcatalog", 
      "usdanationalagriculturallibrary", 
      "biodiversity", 
      "fedlink", 
      "americana"
    ], 
    "volume": "1913", 
    "repub_seconds": "1086", 
    "updater": "associate-manuel-dennis@archive.org", 
    "updatedate": "2015-08-12 15:56:19", 
    "uploader": "associate-manuel-dennis@archive.org", 
    "date": "1913", 
    "republisher": "associate-john-leonard@archive.org", 
    "addeddate": "2015-08-12 15:56:21.433418", 
    "publisher": "Tarrytown-on-Hudson, N.Y. : F.R. Pierson Co.", 
    "publicdate": "2015-08-12 14:50:14", 
    "language": "eng", 
    "page-progression": "lr", 
    "notes": "No copyright page found. No table-of-contents pages found.", 
    "imagecount": "20", 
    "identifier": "CAT31294153", 
    "unique_id": "CAT31294153", 
    "scandate": "20150817112217"
  }, 
  "files_count": 21, 
  "d1": "ia601303.us.archive.org"
}