{
  "files": [
    {
      "sha1": "d83b9a9d4a5e28120ecffaeaca13c0aedd6096c5", 
      "name": "mrstheodosiabshe1897theo_dc.xml", 
      "format": "Dublin Core", 
      "source": "original", 
      "mtime": "1366053928", 
      "crc32": "31c348cd", 
      "md5": "a564b8f4b47fd41f68192aee6f38cff3", 
      "size": "1021"
    }, 
    {
      "sha1": "ee1cf3b20b92550568a2d9f1b9dd3b705450e799", 
      "name": "mrstheodosiabshe1897theo_metasource.xml", 
      "format": "MARC Source", 
      "source": "original", 
      "mtime": "1366053928", 
      "crc32": "fecb758d", 
      "md5": "4a7fa70aa42f3b87eb95d02de76f1487", 
      "size": "411"
    }, 
    {
      "sha1": "a5cecd550e316a8595fd56868806295a8fa24c79", 
      "name": "mrstheodosiabshe1897theo_meta.mrc", 
      "format": "MARC Binary", 
      "source": "original", 
      "mtime": "1366053928", 
      "crc32": "cdbfaadd", 
      "md5": "87b37fb65b063958111f53f6b3458adb", 
      "size": "1233"
    }, 
    {
      "sha1": "89a9637f17ea3e0f22603d00723933a9b7b25c65", 
      "name": "mrstheodosiabshe1897theo_marc.xml", 
      "format": "MARC", 
      "source": "original", 
      "mtime": "1366053928", 
      "crc32": "40b2ecb2", 
      "md5": "07c8a178eb7ce0b5ee50acfb8249086d", 
      "size": "4140"
    }, 
    {
      "sha1": "6549803f0491d0770c87dd4c64cd4ea8c05b5962", 
      "name": "mrstheodosiabshe1897theo_orig_jp2.tar", 
      "format": "Single Page Original JP2 Tar", 
      "source": "original", 
      "mtime": "1366654384", 
      "crc32": "6d9d5253", 
      "md5": "e000af003a61fc6848b306a44b7ff04e", 
      "size": "117524480"
    }, 
    {
      "sha1": "3055c0174d755711af55bdb00e3ca5914a90faf2", 
      "name": "mrstheodosiabshe1897theo_scandata.xml", 
      "format": "Scandata", 
      "source": "original", 
      "mtime": "1366654382", 
      "crc32": "516fe302", 
      "md5": "a9ab6b678dbc21d4f014aee06e77e0a5", 
      "size": "120204"
    }, 
    {
      "sha1": "0ab0906758ed8612b71b3abfa6a7b4c50f2c777e", 
      "name": "mrstheodosiabshe1897theo.pdf", 
      "format": "Text PDF", 
      "source": "derivative", 
      "mtime": "1366693980", 
      "crc32": "39893dd4", 
      "md5": "6950403f828424e7b60094f4fe375771", 
      "original": "mrstheodosiabshe1897theo_djvu.xml", 
      "size": "6698603"
    }, 
    {
      "sha1": "1e02c1c0cf939d586ce2037d1082a44c1ad6e41c", 
      "name": "mrstheodosiabshe1897theo_jp2.zip", 
      "format": "Single Page Processed JP2 ZIP", 
      "source": "derivative", 
      "mtime": "1366692451", 
      "crc32": "28895f9e", 
      "md5": "872332205632767953817ef23b54b0ee", 
      "original": "mrstheodosiabshe1897theo_orig_jp2.tar", 
      "size": "69237464"
    }, 
    {
      "sha1": "b4db8fe26b4ae60ea69e22ffaf6dc2179fd9f7f3", 
      "name": "mrstheodosiabshe1897theo_djvu.xml", 
      "format": "Djvu XML", 
      "source": "derivative", 
      "mtime": "1366693204", 
      "crc32": "75b2e65f", 
      "md5": "f24957cbc9603fc6cc5aecae5cc6b0c5", 
      "original": "mrstheodosiabshe1897theo_abbyy.gz", 
      "size": "1945341"
    }, 
    {
      "sha1": "033f972a5702190e4fe515967c0a21d4aff925b0", 
      "name": "mrstheodosiabshe1897theo_djvu.txt", 
      "format": "DjVuTXT", 
      "source": "derivative", 
      "mtime": "1366693991", 
      "crc32": "282d5170", 
      "md5": "f0a6d1a166e230928c64b1ffee674e31", 
      "original": "mrstheodosiabshe1897theo.djvu", 
      "size": "215432"
    }, 
    {
      "sha1": "1137f05374c128352abc77abc10a4bdf4a05bfdf", 
      "name": "mrstheodosiabshe1897theo.djvu", 
      "format": "DjVu", 
      "source": "derivative", 
      "mtime": "1366693512", 
      "crc32": "9a54bf60", 
      "md5": "9c2a43f47fe886671b3ca3e6cb687904", 
      "original": "mrstheodosiabshe1897theo_djvu.xml", 
      "size": "3545956"
    }, 
    {
      "sha1": "36b22c7eb83935f117a4f5611e86cc42ee403a08", 
      "name": "mrstheodosiabshe1897theo.gif", 
      "format": "Animated GIF", 
      "source": "derivative", 
      "mtime": "1366692474", 
      "crc32": "a5a9ce05", 
      "md5": "4eb45513f2ccc45aa0552758304b7dfa", 
      "original": "mrstheodosiabshe1897theo_jp2.zip", 
      "size": "295504"
    }, 
    {
      "sha1": "272c1f5ce807fba95f9a2b9a2beda68e0bef2b21", 
      "name": "mrstheodosiabshe1897theo_abbyy.gz", 
      "format": "Abbyy GZ", 
      "source": "derivative", 
      "mtime": "1366693150", 
      "crc32": "491a5462", 
      "md5": "0474cc5843beecf6441a3170b151b492", 
      "original": "mrstheodosiabshe1897theo_jp2.zip", 
      "size": "3383073"
    }, 
    {
      "sha1": "0ac1b381e9c481a878eabaac5733bdad6f892160", 
      "name": "mrstheodosiabshe1897theo.epub", 
      "format": "EPUB", 
      "source": "derivative", 
      "mtime": "1366693224", 
      "crc32": "e861ba9d", 
      "md5": "6e0105177c9d1f031aafc237546c1fcc", 
      "original": "mrstheodosiabshe1897theo_abbyy.gz", 
      "size": "398453"
    }, 
    {
      "sha1": "eea72598dc09bcb3bac74db2cf75660e938c16d6", 
      "name": "mrstheodosiabshe1897theo_meta.xml", 
      "format": "Metadata", 
      "source": "original", 
      "mtime": "1418947963", 
      "crc32": "b54db43a", 
      "md5": "452ef67a5299ad23267e2bdbeb37fe2d", 
      "size": "2865"
    }, 
    {
      "sha1": "c3b42930091fd4515159c2451abf7d2001748174", 
      "name": "mrstheodosiabshe1897theo_archive.torrent", 
      "btih": "be86d9b56578455c45670a500beb3f0f9bd83252", 
      "format": "Archive BitTorrent", 
      "source": "metadata", 
      "mtime": "1418947965", 
      "crc32": "9781b0b4", 
      "md5": "0c43426bc9af401d309ca5359bf99db3", 
      "size": "7087"
    }, 
    {
      "source": "original", 
      "md5": "d42dc819553d80e398b5441528a7debb", 
      "name": "mrstheodosiabshe1897theo_files.xml", 
      "format": "Metadata"
    }
  ], 
  "updated": 1446749377, 
  "uniq": 596618858, 
  "created": 1446679445, 
  "workable_servers": [
    "ia801700.us.archive.org", 
    "ia601700.us.archive.org"
  ], 
  "server": "ia801700.us.archive.org", 
  "item_size": 203381267, 
  "dir": "/17/items/mrstheodosiabshe1897theo", 
  "metadata": {
    "shiptracking": "SC0005b", 
    "scanner": "scribe3.beltsville.archive.org", 
    "creator": [
      "Theodosia B. Shepherd Company", 
      "Henry G. Gilbert Nursery and Seed Trade Catalog Collection"
    ], 
    "series": "Henry G. Gilbert Nursery and Seed Trade Catalog Collection", 
    "ppi": "500", 
    "nal_call_number": "62.09", 
    "operator": "associate-kellen-goodwin@archive.org", 
    "sponsor": "U.S. Department of Agriculture, National Agricultural Library", 
    "contributor": "U.S. Department of Agriculture, National Agricultural Library", 
    "foldoutcount": "0", 
    "scanfee": "150", 
    "subject": [
      "Seed industry and trade Catalogs", 
      "Seeds Catalogs", 
      "Flowers Seeds Catalogs", 
      "Plants, Ornamental Catalogs", 
      "Nurseries (Horticulture) Catalogs", 
      "Cactus Seeds Catalogs"
    ], 
    "call_number": "CAT31116283", 
    "title": "Mrs. Theodosia B. Shepherd's descriptive catalogue of California flowers : plants seeds bulbs palms cacti", 
    "repub_state": "4", 
    "possible-copyright-status": "The contributing institution believes that this item is not in copyright", 
    "camera": "Canon EOS 5D Mark II", 
    "addeddate": "2013-04-15 19:25:31", 
    "ocr": "ABBYY FineReader 8.0", 
    "identifier-access": "http://archive.org/details/mrstheodosiabshe1897theo", 
    "scanningcenter": "beltsville", 
    "description": [
      "Cover title", 
      "Includes index"
    ], 
    "identifier-ark": "ark:/13960/t9d526m4z", 
    "mediatype": "texts", 
    "collection": [
      "usda-nurseryandseedcatalog", 
      "usdanationalagriculturallibrary", 
      "fedlink", 
      "americana", 
      "biodiversity"
    ], 
    "volume": "1897", 
    "repub_seconds": "434494", 
    "updater": "associate-adrianna-flores", 
    "updatedate": "2013-04-15 19:25:28", 
    "uploader": "associate-adrianna-flores@archive.org", 
    "date": "1897", 
    "republisher": "associate-kellen-goodwin@archive.org", 
    "identifier-bib": "CAT31116283", 
    "publisher": "Ventura-by-the-Sea, Calif. : Theodosia B. Shepherd Co.", 
    "publicdate": "2013-04-15 19:25:37", 
    "language": "eng", 
    "page-progression": "lr", 
    "curation": "[curator]admin-shelia-deroche@archive.org[/curator][date]20130426192812[/date][state]approved[/state][comment]199[/comment]", 
    "imagecount": "76", 
    "identifier": "mrstheodosiabshe1897theo", 
    "sponsordate": "20130430", 
    "unique_id": "CAT31116283", 
    "scandate": "20130417144520"
  }, 
  "d2": "ia801700.us.archive.org", 
  "files_count": 17, 
  "d1": "ia601700.us.archive.org"
}